{
              "experiment": {
                "id": "e98651",
                "name": "Cepstral Analysis of Speech",
                "overview": "This experiment deals with Cepstral Analysis of Speech",
                "sections": [
                "Aim", 
 							 "Theory", 
 							 "Procedure", 
 							 "Pre Quiz", 
 							 "Simulation", 
 							 "Post Quiz", 
 							 "Assignment", 
 							 "Slot Booking", 
 							 "Reference", 
 							 "Feedback" 
                ]
              },
              "content-type": "org"
            }