{
              "experiment": {
                "id": "e98549",
                "name": "Permeability Experiment",
                "overview": "This experiment deals with Permeability Experiment",
                "sections": [
                "INTRODUCTION", 
 							 "THEORY", 
 							 "OBJECTIVE", 
 							 "EXPERIMENT", 
 							 "MANUAL", 
 							 "QUIZZES", 
 							 "PROCEDURE", 
 							 "FURTHER READINGS" 
                ]
              },
              "content-type": "org"
            }